./.gitignore
./PKG-INFO
./README.md
./__init__.py
./classify_video_zero_shot.py
./pyproject.toml
./test.py
feluda_classify_video_zero_shot-0.2.0.dist-info/METADATA
feluda_classify_video_zero_shot-0.2.0.dist-info/WHEEL
feluda_classify_video_zero_shot-0.2.0.dist-info/RECORD
