Metadata-Version: 2.4
Name: feluda-classify-video-zero-shot
Version: 0.2.0
Requires-Python: >=3.10
Requires-Dist: feluda[video]
Requires-Dist: pillow>=11.1.0
Requires-Dist: torch>=2.6.0
Requires-Dist: transformers>=4.51.1
